table_fifth-0.0.4.dist-info/METADATA
table_fifth-0.0.4.dist-info/WHEEL
table_fifth-0.0.4.dist-info/license_files/LICENSE
table_fifth/__init__.py
table_fifth/__init__.pyi
table_fifth/py.typed
table_fifth/table_fifth.abi3.so
table_fifth-0.0.4.dist-info/RECORD
